grimpulsivewaves/__init__.py
grimpulsivewaves/coordinates/__init__.py
grimpulsivewaves/coordinates/coordinates.py
grimpulsivewaves/integrators/__init__.py
grimpulsivewaves/integrators/geodesic_integrator.py
grimpulsivewaves/plotting/__init__.py
grimpulsivewaves/plotting/dynamic.py
grimpulsivewaves/plotting/static.py
grimpulsivewaves/waves/__init__.py
grimpulsivewaves/waves/solutions.py
GRImpulsiveWaves-0.3.2.dist-info/LICENSE.txt
GRImpulsiveWaves-0.3.2.dist-info/METADATA
GRImpulsiveWaves-0.3.2.dist-info/WHEEL
GRImpulsiveWaves-0.3.2.dist-info/top_level.txt
GRImpulsiveWaves-0.3.2.dist-info/RECORD
