Metadata-Version: 2.1
Name: GRImpulsiveWaves
Version: 0.3.2
Summary: Visualisation of geodesics in impulsive spacetimes using refraction equations.
Home-page: UNKNOWN
Author: Daniel Rod
Author-email: daniel.rod@seznam.cz
License: GNU GPLv3
Platform: UNKNOWN
Requires-Python: >=3.6
Requires-Dist: numpy
Requires-Dist: scipy
Requires-Dist: matplotlib
